mfdls/__init__.py
mfdls/__main__.py
mfdls/completions.py
mfdls/hover.py
mfdls/medford_syntax.py
mfdls/medford_tokens.py
mfdls/medford_validation.py
mfdls/pip_helpers.py
mfdls/server.py
mfdls-0.1.1.dist-info/METADATA
mfdls-0.1.1.dist-info/WHEEL
mfdls-0.1.1.dist-info/licenses/LICENSE
mfdls-0.1.1.dist-info/RECORD
