Metadata-Version: 2.1
Name: mfdls
Version: 0.1.1
Summary: A language server, implementing the Language Server Protocol, for the MEDFORD metadata markup language.
Project-URL: homepage, https://github.com/liam-strand/medford-language-server/
Project-URL: repository, https://github.com/liam-strand/medford-language-server/
Author-email: Liam Strand <Liam.Strand@tufts.edu>, Andrew Powers <andrew_powers@uri.edu>
Classifier: Development Status :: 3 - Alpha
Classifier: Intended Audience :: Science/Research
Classifier: Operating System :: OS Independent
Classifier: Programming Language :: Python :: 3
Classifier: Topic :: Text Editors :: Integrated Development Environments (IDE)
Classifier: Topic :: Text Processing :: Markup
Requires-Python: >=3.8
